bluejayson/__init__.py
bluejayson/__metadata__.py
bluejayson/exceptions.py
bluejayson/fields.py
bluejayson/formatters.py
bluejayson/parsers.py
bluejayson/sanitizers.py
bluejayson/schema.py
bluejayson/validators.py
bluejayson/validators_test.py
BlueJayson-0.1.0.dev1.dist-info/LICENSE
BlueJayson-0.1.0.dev1.dist-info/METADATA
BlueJayson-0.1.0.dev1.dist-info/WHEEL
BlueJayson-0.1.0.dev1.dist-info/top_level.txt
BlueJayson-0.1.0.dev1.dist-info/RECORD
