Metadata-Version: 2.1
Name: BlueJayson
Version: 0.1.0.dev1
Summary: BlueJayson is a simple Pythonic data definition library to manage very basic data validations and serializations to and from JSON.
Home-page: https://github.com/abhabongse/bluejayson
Author: Abhabongse Janthong
Author-email: abhabongse@gmail.com
License: Apache License 2.0
Keywords: schema data-definition json
Platform: UNKNOWN
Classifier: Development Status :: 2 - Pre-Alpha
Classifier: License :: OSI Approved :: Apache Software License
Classifier: Programming Language :: Python
Classifier: Programming Language :: Python :: 3
Classifier: Programming Language :: Python :: 3.6
Classifier: Programming Language :: Python :: 3.7
Classifier: Programming Language :: Python :: 3 :: Only
Classifier: Topic :: Software Development :: Libraries
Requires-Python: >=3.6.0,<4
